sqlalchemy_querybuilder/__init__.py
sqlalchemy_querybuilder/exceptions.py
sqlalchemy_querybuilder/sqlalchemy_querybuilder.py
sqlalchemy_querybuilder-0.1.5.dist-info/COPYING
sqlalchemy_querybuilder-0.1.5.dist-info/WHEEL
sqlalchemy_querybuilder-0.1.5.dist-info/METADATA
sqlalchemy_querybuilder-0.1.5.dist-info/RECORD
