Metadata-Version: 2.1
Name: sqlalchemy-querybuilder
Version: 0.1.5
Summary: Build sqlalchemy queries from jQuery-Query json
Home-page: https://sr.ht/~ocurero/sqlalchemy-querybuilder/
License: Apache-2.0
Keywords: sqlalchemy,jquery,json,querybuilder
Author: Oscar Curero
Author-email: oscar@curero.es
Requires-Python: >=3.6,<4.0
Classifier: Development Status :: 5 - Production/Stable
Classifier: Intended Audience :: Developers
Classifier: License :: OSI Approved :: Apache Software License
Classifier: Programming Language :: Python :: 3
Classifier: Programming Language :: Python :: 3.6
Classifier: Programming Language :: Python :: 3.7
Classifier: Programming Language :: Python :: 3.8
Classifier: Programming Language :: Python :: 3.9
Classifier: Topic :: Software Development :: Libraries
Requires-Dist: sqlalchemy
Project-URL: Documentation, https://sqlalchemy-querybuilder.readthedocs.io/
Project-URL: Repository, https://hg.sr.ht/~ocurero/sqlalchemy-querybuilder
